azure/mgmt/workloadmonitor/__init__.py
azure/mgmt/workloadmonitor/_configuration.py
azure/mgmt/workloadmonitor/_patch.py
azure/mgmt/workloadmonitor/_serialization.py
azure/mgmt/workloadmonitor/_vendor.py
azure/mgmt/workloadmonitor/_version.py
azure/mgmt/workloadmonitor/_workload_monitor_api.py
azure/mgmt/workloadmonitor/py.typed
azure/mgmt/workloadmonitor/aio/__init__.py
azure/mgmt/workloadmonitor/aio/_configuration.py
azure/mgmt/workloadmonitor/aio/_patch.py
azure/mgmt/workloadmonitor/aio/_workload_monitor_api.py
azure/mgmt/workloadmonitor/aio/operations/__init__.py
azure/mgmt/workloadmonitor/aio/operations/_health_monitors_operations.py
azure/mgmt/workloadmonitor/aio/operations/_operations.py
azure/mgmt/workloadmonitor/aio/operations/_patch.py
azure/mgmt/workloadmonitor/models/__init__.py
azure/mgmt/workloadmonitor/models/_models_py3.py
azure/mgmt/workloadmonitor/models/_patch.py
azure/mgmt/workloadmonitor/models/_workload_monitor_api_enums.py
azure/mgmt/workloadmonitor/operations/__init__.py
azure/mgmt/workloadmonitor/operations/_health_monitors_operations.py
azure/mgmt/workloadmonitor/operations/_operations.py
azure/mgmt/workloadmonitor/operations/_patch.py
azure_mgmt_workloadmonitor-1.0.0b4.dist-info/LICENSE
azure_mgmt_workloadmonitor-1.0.0b4.dist-info/METADATA
azure_mgmt_workloadmonitor-1.0.0b4.dist-info/WHEEL
azure_mgmt_workloadmonitor-1.0.0b4.dist-info/top_level.txt
azure_mgmt_workloadmonitor-1.0.0b4.dist-info/RECORD
